octopusdash/README.md
octopusdash/__init__.py
octopusdash/admin.py
octopusdash/apps.py
octopusdash/context.py
octopusdash/exceptions.py
octopusdash/models.py
octopusdash/permissions.py
octopusdash/tests.py
octopusdash/contrib/__init__.py
octopusdash/contrib/admin.py
octopusdash/contrib/managers.py
octopusdash/fields/__init__.py
octopusdash/fields/fields.py
octopusdash/fields/custom/__init__.py
octopusdash/fields/custom/filters/__init__.py
octopusdash/fields/custom/filters/fields.py
octopusdash/fields/custom/filters/widgets.py
octopusdash/forms/__init__.py
octopusdash/forms/model_forms.py
octopusdash/middlewares/__init__.py
octopusdash/middlewares/app.py
octopusdash/middlewares/authentication.py
octopusdash/migrations/__init__.py
octopusdash/migrations/__pycache__/__init__.cpython-312.pyc
octopusdash/registry/__init__.py
octopusdash/registry/_exceptions.py
octopusdash/registry/admin.py
octopusdash/registry/app_registry.py
octopusdash/registry/decorators.py
octopusdash/registry/metaclasses.py
octopusdash/static/od/css/styles.min.css
octopusdash/static/od/css/tailwind.css
octopusdash/static/od/css/components/_bars.scss
octopusdash/static/od/css/components/_buttons.scss
octopusdash/static/od/css/components/_checkbox.scss
octopusdash/static/od/css/components/_date_inputs.scss
octopusdash/static/od/css/components/_inputs.scss
octopusdash/static/od/css/components/_multi_select.scss
octopusdash/static/od/css/components/_radio_input.scss
octopusdash/static/od/css/components/_table.scss
octopusdash/static/od/css/components/_textarea.scss
octopusdash/static/od/css/components/_timeline.scss
octopusdash/static/od/css/components/buttons/button.min.css
octopusdash/static/od/css/components/buttons/button.min.css.map
octopusdash/static/od/css/components/buttons/button.scss
octopusdash/static/od/css/components/custom/datepicker/datepicker.min.css
octopusdash/static/od/css/components/custom/datepicker/datepicker.min.css.map
octopusdash-0.1.2.dist-info/licenses/LICENSE
octopusdash-0.1.2.dist-info/METADATA
octopusdash-0.1.2.dist-info/WHEEL
octopusdash-0.1.2.dist-info/top_level.txt
octopusdash-0.1.2.dist-info/RECORD
