Metadata-Version: 2.4
Name: octopusdash
Version: 0.1.2
Summary: A modern open-source Django admin dashboard.
Home-page: https://github.com/husseinnaeemsec/octopusdash
Author: Hussein Naeem
Author-email: Hussein Naeem <husseinnaeemsec@gmail.com>
License: MIT
Project-URL: Homepage, https://github.com/husseinnaeemsec/octopusdash
Project-URL: Repository, https://github.com/husseinnaeemsec/octopusdash
Requires-Python: >=3.8
License-File: LICENSE
Requires-Dist: Django>=4.0
Dynamic: license-file
